.long-description.html
README.rst
setup.py
src/Products/__init__.py
src/Products.PFGExtendedMailAdapter.egg-info/PKG-INFO
src/Products.PFGExtendedMailAdapter.egg-info/SOURCES.txt
src/Products.PFGExtendedMailAdapter.egg-info/dependency_links.txt
src/Products.PFGExtendedMailAdapter.egg-info/entry_points.txt
src/Products.PFGExtendedMailAdapter.egg-info/namespace_packages.txt
src/Products.PFGExtendedMailAdapter.egg-info/not-zip-safe
src/Products.PFGExtendedMailAdapter.egg-info/requires.txt
src/Products.PFGExtendedMailAdapter.egg-info/top_level.txt
src/Products/PFGExtendedMailAdapter/__init__.py
src/Products/PFGExtendedMailAdapter/configure.zcml
src/Products/PFGExtendedMailAdapter/interfaces.py
src/Products/PFGExtendedMailAdapter/content/__init__.py
src/Products/PFGExtendedMailAdapter/content/adapter.py
src/Products/PFGExtendedMailAdapter/content/configure.zcml
src/Products/PFGExtendedMailAdapter/docs/CREDITS.rst
src/Products/PFGExtendedMailAdapter/docs/HISTORY.rst
src/Products/PFGExtendedMailAdapter/docs/INSTALL.rst
src/Products/PFGExtendedMailAdapter/docs/LICENSE.rst
src/Products/PFGExtendedMailAdapter/docs/Makefile
src/Products/PFGExtendedMailAdapter/docs/README.rst
src/Products/PFGExtendedMailAdapter/docs/conf.py
src/Products/PFGExtendedMailAdapter/docs/index.rst
src/Products/PFGExtendedMailAdapter/docs/_static/.gitignore
src/Products/PFGExtendedMailAdapter/locales/Products.PFGExtendedMailAdapter.pot
src/Products/PFGExtendedMailAdapter/locales/fi/LC_MESSAGES/Products.PFGExtendedMailAdapter.po
src/Products/PFGExtendedMailAdapter/profiles/default/factorytool.xml
src/Products/PFGExtendedMailAdapter/profiles/default/metadata.xml
src/Products/PFGExtendedMailAdapter/profiles/default/propertiestool.xml
src/Products/PFGExtendedMailAdapter/profiles/default/rolemap.xml
src/Products/PFGExtendedMailAdapter/profiles/default/types.xml
src/Products/PFGExtendedMailAdapter/profiles/default/workflows.xml
src/Products/PFGExtendedMailAdapter/profiles/default/types/FormFolder.xml
src/Products/PFGExtendedMailAdapter/profiles/default/types/PFGExtendedMailAdapter.xml
src/Products/PFGExtendedMailAdapter/tests/__init__.py
src/Products/PFGExtendedMailAdapter/tests/base.py
src/Products/PFGExtendedMailAdapter/tests/test_PFGExtendedMailAdapter.py
src/Products/PFGExtendedMailAdapter/tests/test_functional.py
src/Products/PFGExtendedMailAdapter/tests/test_setup.py
src/Products/PFGExtendedMailAdapter/tests/functional/content_types_functional.txt
