Metadata-Version: 1.1
Name: Products.PFGExtendedMailAdapter
Version: 2.4
Summary: Adds extended mail adapter to Products.PloneFormGen.
Home-page: https://github.com/collective/Products.PFGExtendedMailAdapter
Author: Taito Horiuchi
Author-email: taito.horiuchi@gmail.com
License: BSD
Platform: UNKNOWN
Classifier: Framework :: Plone
Classifier: Framework :: Plone :: 4.2
Classifier: Framework :: Plone :: 4.3
Classifier: License :: OSI Approved :: BSD License
Classifier: Programming Language :: Python
Classifier: Programming Language :: Python :: 2.7
